nasa/__init__.py
nasa/abc.py
nasa/client.py
nasa/errors.py
nasa/http.py
nasa/models/__init__.py
nasa/models/apod.py
nasa/models/meta.py
nasa.py-0.2.0.dist-info/LICENSE
nasa.py-0.2.0.dist-info/METADATA
nasa.py-0.2.0.dist-info/WHEEL
nasa.py-0.2.0.dist-info/top_level.txt
nasa.py-0.2.0.dist-info/RECORD
