Metadata-Version: 2.1
Name: nasa.py
Version: 0.2.0
Summary: An async ready wrapper for the NASA Open API's
Home-page: UNKNOWN
Author: quiktea
Author-email: wishymovies@gmail.com
License: UNKNOWN
Project-URL: GitHub, https://github.com/quiktea/nasa.py
Keywords: python,nasa,api,mars,rover
Platform: UNKNOWN
Classifier: Development Status :: 1 - Planning
Classifier: Intended Audience :: Developers
Classifier: Programming Language :: Python :: 3
Classifier: Operating System :: Unix
Classifier: Operating System :: MacOS :: MacOS X
Classifier: Operating System :: Microsoft :: Windows
Requires-Dist: aiohttp
Provides-Extra: speedups
Requires-Dist: aiohttp[speedups] ; extra == 'speedups'
